dummy_pkg_for_tests_with_deps/__init__.py
dummy_pkg_for_tests_with_deps/shrubbery.py
dummy_pkg_for_tests_with_deps-1.0.dist-info/METADATA
dummy_pkg_for_tests_with_deps-1.0.dist-info/WHEEL
dummy_pkg_for_tests_with_deps-1.0.dist-info/licenses/LICENSE
dummy_pkg_for_tests_with_deps-1.0.dist-info/RECORD
